{
  "broadcast_id": "28178606096",
  "broadcaster": {
    "channel_url": "https://www.twitch.tv/devicat",
    "display_name": "DeviCat",
    "id": "54212603",
    "logo": "https://static-cdn.jtvnw.net/jtv_user_pictures/15c9f664-be7b-4d13-9842-9dd2be69a856-profile_image-150x150.png",
    "name": "devicat"
  },
  "created_at": "2018-04-02T21:02:41Z",
  "curator": {
    "channel_url": "https://www.twitch.tv/sakurakoneko",
    "display_name": "SakuraKoneko",
    "id": "131364305",
    "logo": "https://static-cdn.jtvnw.net/jtv_user_pictures/4cb43e72-62e7-4f2f-9678-dcea169ff9a5-profile_image-150x150.jpg",
    "name": "sakurakoneko"
  },
  "duration": 30,
  "embed_html": "<iframe src='https://clips.twitch.tv/embed?clip=SpineyMildRhinocerosBleedPurple&tt_medium=clips_api&tt_content=embed' width='640' height='360' frameborder='0' scrolling='no' allowfullscreen='true'></iframe>",
  "embed_url": "https://clips.twitch.tv/embed?clip=SpineyMildRhinocerosBleedPurple&tt_medium=clips_api&tt_content=embed",
  "game": "creative",
  "language": "en",
  "slug": "SpineyMildRhinocerosBleedPurple",
  "thumbnails": {
    "medium": "https://clips-media-assets2.twitch.tv/218464683-preview-480x272.jpg",
    "small": "https://clips-media-assets2.twitch.tv/218464683-preview-260x147.jpg",
    "tiny": "https://clips-media-assets2.twitch.tv/218464683-preview-86x45.jpg"
  },
  "title": "Devi's waiting Dance for Photoshop to load",
  "tracking_id": "218464683",
  "url": "https://clips.twitch.tv/SpineyMildRhinocerosBleedPurple?tt_medium=clips_api&tt_content=url",
  "views": 6,
  "vod": null
}